rapidcli/__init__.py
rapidcli/app_loader.py
rapidcli/cli.py
rapidcli/config_registrar.py
rapidcli/exceptions.py
rapidcli/extension.py
rapidcli/extension_registrar.py
rapidcli/rapid_admin/__init__.py
rapidcli/rapid_admin/admin/admin.py
rapidcli/rapid_admin/admin/app_config.yml
rapidcli/rapid_admin/admin/configs.py
rapidcli/rapid_admin/cli_config.yml
rapidcli/rapid_admin/rapid_admin.py
rapidcli/rapid_admin/templates/rapidcli_app_template/app_config.ryml
rapidcli/rapid_admin/templates/rapidcli_app_template/configs.rpy
rapidcli/rapid_admin/templates/rapidcli_app_template/extensions.rpy
rapidcli/rapid_admin/templates/rapidcli_cli_template/cli.rpy
rapidcli/rapid_admin/templates/rapidcli_cli_template/cli_config.rpy
rapidcli/settings.py
rapidcli/tests/__init__.py
rapidcli/tests/app_config.yml
rapidcli/tests/cli_config.yml
rapidcli/tests/cli_test_configs.py
rapidcli/tests/config_tests.py
rapidcli/tests/util_tests.py
rapidcli/utils.py
rapidcli-0.1.4.dist-info/entry_points.txt
rapidcli-0.1.4.dist-info/WHEEL
rapidcli-0.1.4.dist-info/METADATA
rapidcli-0.1.4.dist-info/RECORD
