Metadata-Version: 2.1
Name: rapidcli
Version: 0.1.4
Summary: A rapid CLI framework meant for developers who need complex solutions with minimal work.
Author: benjamin garrard
Author-email: benjamingarrard5279@gmail.com
Requires-Python: >=3.8,<4.0
Classifier: Programming Language :: Python :: 3
Classifier: Programming Language :: Python :: 3.10
Classifier: Programming Language :: Python :: 3.8
Classifier: Programming Language :: Python :: 3.9
Requires-Dist: GitPython (>=3.1.27,<4.0.0)
Requires-Dist: Jinja2 (>=3.1.2,<4.0.0)
Requires-Dist: PyYAML (>=6.0,<7.0)
Requires-Dist: pandas (>=1.4.2,<2.0.0)
Requires-Dist: protobuf (>=4.21.1,<5.0.0)
Requires-Dist: tqdm (>=4.64.0,<5.0.0)
